spellcraft-0.1.1.dist-info/METADATA
spellcraft-0.1.1.dist-info/WHEEL
spellcraft-0.1.1.dist-info/licenses/LICENSE
spellcraft/__init__.py
spellcraft/__init__.pyi
spellcraft/py.typed
spellcraft/spellcraft.pyd
spellcraft-0.1.1.dist-info/RECORD
