Metadata-Version: 2.3
Name: spellcraft
Version: 0.1.1
Classifier: Programming Language :: Python :: Implementation :: CPython
Classifier: Programming Language :: Python :: Implementation :: PyPy
Classifier: Programming Language :: Python :: 3
Classifier: Programming Language :: Python :: 3.9
Classifier: Programming Language :: Python :: 3.10
Classifier: Programming Language :: Python :: 3.11
Classifier: Programming Language :: Python :: 3.12
Classifier: Programming Language :: Python :: 3.13
Classifier: License :: OSI Approved :: MIT License
Classifier: Operating System :: OS Independent
Classifier: Programming Language :: Rust
Requires-Dist: maturin >=1.7, <2.0 ; extra == 'dev'
Requires-Dist: black ~=24.10.0 ; extra == 'dev'
Requires-Dist: mypy ~=1.13.0 ; extra == 'dev'
Requires-Dist: pytest ~=8.3.3 ; extra == 'dev'
Requires-Dist: pytest-benchmark ~=5.1.0 ; extra == 'dev'
Requires-Dist: flake8 ~=7.1.1 ; extra == 'dev'
Requires-Dist: bump2version ~=1.0.1 ; extra == 'dev'
Requires-Dist: myst-parser ~=4.0.0 ; extra == 'dev'
Requires-Dist: sphinx ~=8.1.3 ; extra == 'dev'
Requires-Dist: sphinx-autobuild ==2024.10.3 ; extra == 'dev'
Requires-Dist: sphinx-material ~=0.0.36 ; extra == 'dev'
Requires-Dist: myst-parser ~=4.0.0 ; extra == 'sphinx'
Requires-Dist: sphinx ~=8.1.3 ; extra == 'sphinx'
Requires-Dist: sphinx-autobuild ==2024.10.3 ; extra == 'sphinx'
Requires-Dist: sphinx-material ~=0.0.36 ; extra == 'sphinx'
Provides-Extra: dev
Provides-Extra: sphinx
License-File: LICENSE
Summary: spellcraft is a helper library containing useful functions and spells, primarily designed for use by Dataclass Wizard.
Keywords: string,case,camel,snake,unicode
Author-email: rnag <me@ritviknag.com>
License: MIT
Requires-Python: >=3.9
Project-URL: homepage, https://github.com/rnag/spellcraft
Project-URL: documentation, https://rnag.github.io/spellcraft/
Project-URL: repository, https://github.com/rnag/spellcraft
Project-URL: changelog, https://github.com/rnag/spellcraft/blob/main/CHANGELOG.md
